admin_resumable/__init__.py
admin_resumable/fields.py
admin_resumable/files.py
admin_resumable/tests.py
admin_resumable/urls.py
admin_resumable/views.py
admin_resumable/static/admin_resumable/js/resumable.js
admin_resumable/templates/admin_resumable/file_input.html
django_admin_resumable_js-3.0.dist-info/METADATA
django_admin_resumable_js-3.0.dist-info/RECORD
django_admin_resumable_js-3.0.dist-info/WHEEL
django_admin_resumable_js-3.0.dist-info/top_level.txt
