Metadata-Version: 2.1
Name: django-admin-resumable-js
Version: 3.0
Summary: A Django app for the uploading of large files from the django admin site.
Home-page: https://github.com/jonatron/django-admin-resumable-js
Author: Jonatron
Author-email: jon4tron@gmail.com
License: MIT License
Platform: UNKNOWN
Classifier: Environment :: Web Environment
Classifier: Framework :: Django
Classifier: Intended Audience :: Developers
Classifier: License :: OSI Approved :: MIT License
Classifier: Operating System :: OS Independent
Classifier: Programming Language :: Python
Classifier: Programming Language :: Python :: 2.7
Classifier: Topic :: Internet :: WWW/HTTP
Classifier: Topic :: Internet :: WWW/HTTP :: Dynamic Content
